aipowershell/__init__.py
aipowershell/__main__.py
aipowershell/analyzer.py
aipowershell/cli.py
aipowershell/error_handler.py
aipowershell-0.2.0.dist-info/licenses/LICENSE
aipowershell-0.2.0.dist-info/METADATA
aipowershell-0.2.0.dist-info/WHEEL
aipowershell-0.2.0.dist-info/entry_points.txt
aipowershell-0.2.0.dist-info/top_level.txt
aipowershell-0.2.0.dist-info/RECORD
